atlas_provider_django/__init__.py
atlas_provider_django/management/__init__.py
atlas_provider_django/management/commands/__init__.py
atlas_provider_django/management/commands/atlas-provider-django.py
atlas_provider_django/management/commands/migrations.py
atlas_provider_django/settings.py
atlas_provider_django-0.2.4.dist-info/LICENSE
atlas_provider_django-0.2.4.dist-info/METADATA
atlas_provider_django-0.2.4.dist-info/WHEEL
atlas_provider_django-0.2.4.dist-info/RECORD
