Metadata-Version: 2.3
Name: atlas-provider-django
Version: 0.2.4
Summary: 
Author: Atlas Team
Author-email: hello@ariga.io
Requires-Python: >=3.11,<4.0
Classifier: Programming Language :: Python :: 3
Classifier: Programming Language :: Python :: 3.11
Classifier: Programming Language :: Python :: 3.12
Classifier: Programming Language :: Python :: 3.13
Requires-Dist: django (>=4.2)
